simpler_py/__init__.py
simpler_py/simpler.py
simpler_py-1.0.2.dist-info/METADATA
simpler_py-1.0.2.dist-info/WHEEL
simpler_py-1.0.2.dist-info/licenses/LICENSE.txt
simpler_py-1.0.2.dist-info/RECORD
